jama_client/__init__.py
jama_client/__main__.py
jama_client_certic-0.0.35.dist-info/LICENSE.txt
jama_client_certic-0.0.35.dist-info/METADATA
jama_client_certic-0.0.35.dist-info/WHEEL
jama_client_certic-0.0.35.dist-info/RECORD
