Metadata-Version: 2.1
Name: jama-client-certic
Version: 0.0.35
Summary: Jama client for Python
License: CECILL-C
Author: Mickaël Desfrênes
Author-email: mickael.desfrenes@unicaen.fr
Requires-Python: >=3.9.4
Classifier: License :: CeCILL-C Free Software License Agreement (CECILL-C)
Classifier: Programming Language :: Python :: 3
Classifier: Programming Language :: Python :: 3.10
Classifier: Programming Language :: Python :: 3.11
Classifier: Programming Language :: Python :: 3.12
Requires-Dist: argh (>=0.29.4)
Requires-Dist: requests (>=2.31.0)
